atc_profile_storage/__init__.py
atc_profile_storage/models.py
atc_profile_storage/serializers.py
atc_profile_storage/urls.py
atc_profile_storage/views.py
atc_profile_storage/migrations/0001_initial.py
atc_profile_storage/migrations/__init__.py
atc_profile_storage/static/js/atc-profile-storage.js
django_atc_profile_storage-0.1.6.dist-info/DESCRIPTION.rst
django_atc_profile_storage-0.1.6.dist-info/METADATA
django_atc_profile_storage-0.1.6.dist-info/RECORD
django_atc_profile_storage-0.1.6.dist-info/WHEEL
django_atc_profile_storage-0.1.6.dist-info/metadata.json
django_atc_profile_storage-0.1.6.dist-info/top_level.txt
